fbsdk/__init__.py
fbsdk/fb.py
facebook_sdk_py-0.0.2.dist-info/METADATA
facebook_sdk_py-0.0.2.dist-info/WHEEL
facebook_sdk_py-0.0.2.dist-info/top_level.txt
facebook_sdk_py-0.0.2.dist-info/RECORD
