Metadata-Version: 2.1
Name: facebook-sdk-py
Version: 0.0.2
Summary: This client library is designed to support the Facebook Graph API
Home-page: https://github.com/Caivy/fb-sdk-py
Author: Caivy
Author-email: UNKNOWN
License: Apache
Keywords: python,facebook,API,Faccebook Graph API,requests
Platform: UNKNOWN
Classifier: Development Status :: 1 - Planning
Classifier: Intended Audience :: Developers
Classifier: Programming Language :: Python :: 3
Classifier: Operating System :: Unix
Classifier: Operating System :: MacOS :: MacOS X
Classifier: Operating System :: Microsoft :: Windows
Requires-Dist: requests
